sfcpy/__init__.py
sfcpy/__main__.py
sfcpy/data.py
sfcpy/generator.py
sfcpy/hc_lookup.txt
sfcpy/hilbert.py
sfcpy-1.2.3.dist-info/DESCRIPTION.rst
sfcpy-1.2.3.dist-info/METADATA
sfcpy-1.2.3.dist-info/RECORD
sfcpy-1.2.3.dist-info/WHEEL
sfcpy-1.2.3.dist-info/entry_points.txt
sfcpy-1.2.3.dist-info/metadata.json
sfcpy-1.2.3.dist-info/top_level.txt
